COPYING
MANIFEST.in
README.rst
buildout.cfg
environment.yml
requirements.txt
setup.py
bob/__init__.py
bob.paper.isba2018_entropy.egg-info/PKG-INFO
bob.paper.isba2018_entropy.egg-info/SOURCES.txt
bob.paper.isba2018_entropy.egg-info/dependency_links.txt
bob.paper.isba2018_entropy.egg-info/entry_points.txt
bob.paper.isba2018_entropy.egg-info/requires.txt
bob.paper.isba2018_entropy.egg-info/top_level.txt
bob/paper/__init__.py
bob/paper/isba2018_entropy/__init__.py
bob/paper/isba2018_entropy/configurations/__init__.py
bob/paper/isba2018_entropy/configurations/utfvp_mc.py
bob/paper/isba2018_entropy/configurations/utfvp_rlt.py
bob/paper/isba2018_entropy/configurations/utfvp_wld.py
bob/paper/isba2018_entropy/configurations/vera_mc.py
bob/paper/isba2018_entropy/configurations/vera_rlt.py
bob/paper/isba2018_entropy/configurations/vera_wld.py
bob/paper/isba2018_entropy/scripts/__init__.py
bob/paper/isba2018_entropy/scripts/calculate_entropy.py