Metadata-Version: 1.1
Name: bob.paper.isba2018-entropy
Version: 1.0.3
Summary: Calculating the entropy of fingervein patterns
Home-page: https://gitlab.idiap.ch/bob/bob.paper.isba2018_entropy
Author: Vedrana Krivokuca
Author-email: vedrana.krivokuca@idiap.ch
License: GPLv3
Keywords: bob,fingervein recognition,entropy
Platform: UNKNOWN
Classifier: Framework :: Bob
Classifier: Development Status :: 3 - Alpha
Classifier: Intended Audience :: Developers
Classifier: License :: OSI Approved :: GNU General Public License v3 (GPLv3)
Classifier: Natural Language :: English
Classifier: Programming Language :: Python
Classifier: Topic :: Scientific/Engineering :: Artificial Intelligence
